perl/.gitignore
perl/ChangeLog
perl/LICENSE
perl/Makefile.PL
perl/README
perl/doc/pg_format.pod
perl/icon_pgformatter.ico
perl/lib/autodie/Fatal.pm
perl/lib/autodie/autodie/Scope/Guard.pm
perl/lib/autodie/autodie/Scope/GuardStack.pm
perl/lib/autodie/autodie/Util.pm
perl/lib/autodie/autodie/exception/system.pm
perl/lib/autodie/autodie/exception.pm
perl/lib/autodie/autodie/hints.pm
perl/lib/autodie/autodie/skip.pm
perl/lib/autodie/autodie.pm
perl/lib/pgFormatter/Beautify.pm
perl/lib/pgFormatter/CGI.pm
perl/lib/pgFormatter/CLI.pm
perl/logo_pgformatter.png
perl/pg_format
perl/t/01_lint.t
perl/t/02_regress.t
perl/t/pg-test-files/expected/advisory_lock.sql
perl/t/pg-test-files/expected/aggregates.sql
perl/t/pg-test-files/expected/alter_generic.sql
perl/t/pg-test-files/expected/alter_operator.sql
perl/t/pg-test-files/expected/alter_table.sql
perl/t/pg-test-files/expected/amutils.sql
perl/t/pg-test-files/expected/arrays.sql
perl/t/pg-test-files/expected/async.sql
perl/t/pg-test-files/expected/bit.sql
perl/t/pg-test-files/expected/bitmapops.sql
perl/t/pg-test-files/expected/boolean.sql
perl/t/pg-test-files/expected/box.sql
perl/t/pg-test-files/expected/brin.sql
perl/t/pg-test-files/expected/btree_index.sql
perl/t/pg-test-files/expected/case.sql
perl/t/pg-test-files/expected/char.sql
perl/t/pg-test-files/expected/circle.sql
perl/t/pg-test-files/expected/cluster.sql
perl/t/pg-test-files/expected/collate.icu.utf8.sql
perl/t/pg-test-files/expected/collate.linux.utf8.sql
perl/t/pg-test-files/expected/collate.sql
perl/t/pg-test-files/expected/combocid.sql
perl/t/pg-test-files/expected/comments.sql
perl/t/pg-test-files/expected/conversion.sql
perl/t/pg-test-files/expected/create_aggregate.sql
perl/t/pg-test-files/expected/create_am.sql
perl/t/pg-test-files/expected/create_cast.sql
perl/t/pg-test-files/expected/create_function_3.sql
perl/t/pg-test-files/expected/create_index.sql
perl/t/pg-test-files/expected/create_index_spgist.sql
perl/t/pg-test-files/expected/create_misc.sql
pgformatter-0.1.6.dist-info/WHEEL
pgformatter-0.1.6.dist-info/METADATA
pgformatter-0.1.6.dist-info/RECORD
