Metadata-Version: 2.1
Name: pgformatter
Version: 0.1.6
Summary: Thin Python wrapper for pgFormatter
Author: Nathan Cahill
Author-email: nathan@nathancahill.com
Requires-Python: >=3.6,<4.0
Classifier: Programming Language :: Python :: 3
Classifier: Programming Language :: Python :: 3.6
Classifier: Programming Language :: Python :: 3.7
Classifier: Programming Language :: Python :: 3.8
